ensembldb/__init__.py
ensembldb/_ahub.py
ensembldb/ensdb.py
ensembldb/record.py
ensembldb/registry.py
ensembldb-0.0.1.dist-info/licenses/LICENSE.txt
ensembldb-0.0.1.dist-info/METADATA
ensembldb-0.0.1.dist-info/WHEEL
ensembldb-0.0.1.dist-info/top_level.txt
ensembldb-0.0.1.dist-info/RECORD
