Metadata-Version: 2.4
Name: ensembldb
Version: 0.0.1
Summary: Access EnsemblDb resources from Bioconductors AnnotationHub
Home-page: https://github.com/pyscaffold/pyscaffold/
Author: Jayaram Kancherla
Author-email: jayaram.kancherla@gmail.com
License: MIT
Project-URL: Documentation, https://pyscaffold.org/
Platform: any
Classifier: Development Status :: 4 - Beta
Classifier: Programming Language :: Python
License-File: LICENSE.txt
Requires-Dist: importlib-metadata; python_version < "3.8"
Requires-Dist: pybiocfilecache
Requires-Dist: biocframe
Requires-Dist: genomicranges
Requires-Dist: iranges
Provides-Extra: testing
Requires-Dist: setuptools; extra == "testing"
Requires-Dist: pytest; extra == "testing"
Requires-Dist: pytest-cov; extra == "testing"
Dynamic: license-file
